README.rst
setup.py
whatsonchain/__init__.py
whatsonchain/api.py
whatsonchain.egg-info/PKG-INFO
whatsonchain.egg-info/SOURCES.txt
whatsonchain.egg-info/dependency_links.txt
whatsonchain.egg-info/requires.txt
whatsonchain.egg-info/top_level.txt