Metadata-Version: 1.2
Name: whatsonchain
Version: 0.0.1
Summary: Whatsonchain API.
Home-page: https://github.com/AustEcon/whatsonchain
Author: AustEcon
Author-email: AustEcon0922@gmail.com
Maintainer: AustEcon
Maintainer-email: AustEcon0922@gmail.com
License: MIT
Download-URL: https://github.com/AustEcon/whatsonchain/tarball/0.0.1
Keywords: bitcoinsv,bsv,bitcoin sv,cryptocurrency,payments,tools,wallet,whatsonchain
Platform: UNKNOWN
Classifier: Development Status :: 4 - Beta
Classifier: Intended Audience :: Developers
Classifier: Intended Audience :: End Users/Desktop
Classifier: License :: OSI Approved :: MIT License
Classifier: Natural Language :: English
Classifier: Operating System :: OS Independent
Classifier: Programming Language :: Python :: 3.5
Classifier: Programming Language :: Python :: 3.6
Classifier: Programming Language :: Python :: 3.7
Classifier: Programming Language :: Python :: Implementation :: CPython
